{
    "github": {
        "oauth": {
            "baseUrl": "http://localhost",
            "port": 8080,
            "loginUri": "/login",
            "callbackUri": "/callback",
            "scopes": "repo"
        },
        "api": {
            "key": "",
            "secret": "",
            "retries": 3
        }
    },
    "project": {
        "organization": "vroozi",
        "repo": "purchasing-manager"
    },
    "logger": {
        "level": "debug"
    },
    "reports": {
        "userReviewTimeBuckets": {
            "bucketSize": 8,
            "maxBuckets": 7
        }
    }
}
